x_decorator/__init__.py
x_decorator/circuit_breaker_decorator.py
x_decorator/concurrent_decorator.py
x_decorator/count_calls_decorator.py
x_decorator/debug_decorator.py
x_decorator/email_on_failure_decorator.py
x_decorator/log_execution_decorator.py
x_decorator/memoize_decorator.py
x_decorator/queue_processor_decorator.py
x_decorator/rate_limit_decorator.py
x_decorator/retry_decorator.py
x_decorator/run_at_decorator.py
x_decorator/scheduler_decorator.py
x_decorator/singleton_decorator.py
x_decorator/state_machine_decorator.py
x_decorator/timing_decorator.py
x_decorator-1.0.1.dist-info/LICENSE
x_decorator-1.0.1.dist-info/METADATA
x_decorator-1.0.1.dist-info/WHEEL
x_decorator-1.0.1.dist-info/top_level.txt
x_decorator-1.0.1.dist-info/RECORD
